lyywingui
