Metadata-Version: 2.2
Name: lyywingui
Version: 1.2
Summary: lyywingui for lyy
Author: lyy
Author-email: 
License: MIT
License-File: LICENSE
Requires-Dist: psutil>=5.9.0
Requires-Dist: pywin32>=300
Requires-Dist: fuzzywuzzy>=0.18.0
Requires-Dist: python-Levenshtein>=0.12.0
Dynamic: author
Dynamic: license
Dynamic: requires-dist
Dynamic: summary
